cvascode/__init__.py
cvascode/app.py
cvascode-0.1.1.dist-info/METADATA
cvascode-0.1.1.dist-info/WHEEL
cvascode-0.1.1.dist-info/entry_points.txt
cvascode-0.1.1.dist-info/top_level.txt
cvascode-0.1.1.dist-info/RECORD
