Metadata-Version: 2.1
Name: cvascode
Version: 0.1.1
Summary: Utility to generate CVs from templates.
Home-page: https://github.com/benchoncy/cvascode
Author: Ben Stuart
Author-email: ben@benstuart.ie
License: LICENSE
Requires-Dist: pyyaml
Requires-Dist: jinja2
Requires-Dist: schema
Requires-Dist: docxtpl
